MANIFEST.in
README.md
setup.cfg
setup.py
sphinx_enos_theme/__init__.py
sphinx_enos_theme/breadcrumbs.html
sphinx_enos_theme/footer.html
sphinx_enos_theme/gfooter.html
sphinx_enos_theme/header.html
sphinx_enos_theme/layout.html
sphinx_enos_theme/search.html
sphinx_enos_theme/searchbox.html
sphinx_enos_theme/side.html
sphinx_enos_theme/theme.conf
sphinx_enos_theme/tools.html
sphinx_enos_theme.egg-info/PKG-INFO
sphinx_enos_theme.egg-info/SOURCES.txt
sphinx_enos_theme.egg-info/dependency_links.txt
sphinx_enos_theme.egg-info/entry_points.txt
sphinx_enos_theme.egg-info/not-zip-safe
sphinx_enos_theme.egg-info/requires.txt
sphinx_enos_theme.egg-info/top_level.txt
sphinx_enos_theme/static/css/theme.css
sphinx_enos_theme/static/js/docAuthLogin.65b57bf0dc00161610a3.js
sphinx_enos_theme/static/js/theme.e1819d00d6c10c19e3b1.js